{
  "publicPath": "/_nuxt/",
  "all": [
    "../server/index.spa.html",
    "../server/index.ssr.html",
    "13c5661.js",
    "25c4d93.js",
    "38f26bc.js",
    "3be277b.js",
    "4828718.js",
    "5c3d831.js",
    "5d961e2.js",
    "73c76db.js",
    "86ad62f.js",
    "LICENSES",
    "e1782c0.js",
    "ee95317.js"
  ],
  "initial": [
    "73c76db.js",
    "e1782c0.js",
    "86ad62f.js"
  ],
  "async": [
    "13c5661.js",
    "25c4d93.js",
    "38f26bc.js",
    "3be277b.js",
    "4828718.js",
    "5c3d831.js",
    "5d961e2.js",
    "ee95317.js"
  ],
  "modules": {
    "20556450": [
      12
    ],
    "22305770": [
      6
    ],
    "30632522": [
      6
    ],
    "53520878": [
      12
    ],
    "64638202": [
      12
    ],
    "65746511": [
      12
    ],
    "67688104": [
      6
    ],
    "68918252": [
      6
    ],
    "74753836": [
      12
    ],
    "83622966": [
      12
    ],
    "85259010": [
      6
    ],
    "a88c78dc": [
      10
    ],
    "a8746c3e": [
      12
    ],
    "38e25108": [
      12
    ],
    "c7b53874": [
      10
    ],
    "50efb9e4": [
      12
    ],
    "e62dd770": [
      12
    ],
    "52fd6433": [
      12
    ],
    "015e7fba": [
      12
    ],
    "08b1e160": [
      10
    ],
    "48fad5ce": [
      10
    ],
    "52ba7493": [
      10
    ],
    "63362c6a": [
      10
    ],
    "78e46f19": [
      10
    ],
    "22d0ffd8": [
      10
    ],
    "fbd08526": [
      12
    ],
    "f6077f5c": [
      12
    ],
    "33acd48e": [
      12
    ],
    "6b506bf9": [
      12
    ],
    "9a2485f6": [
      12
    ],
    "f244a85e": [
      10
    ],
    "e1d468bc": [
      10
    ],
    "9d6f16ea": [
      10
    ],
    "495d212a": [
      10
    ],
    "183a6b8c": [
      10
    ],
    "f5bac97c": [
      10
    ],
    "32faa53c": [
      10
    ],
    "56408f0f": [
      10
    ],
    "332821df": [
      10
    ],
    "300a1d44": [
      10
    ],
    "8e661944": [
      10
    ],
    "79eb8442": [
      10
    ],
    "5f1d8b56": [
      10
    ],
    "0f0619c8": [
      10
    ],
    "688833c4": [
      10
    ],
    "3b95d66a": [
      10
    ],
    "69f7ba0d": [
      10
    ],
    "4e93192a": [
      10
    ],
    "3e080c12": [
      10
    ],
    "6f6ecf30": [
      12
    ],
    "06c0000f": [
      12
    ],
    "2edd3151": [
      10
    ],
    "1ebcb4ad": [
      12
    ],
    "826f2af6": [
      12
    ],
    "6fd350c6": [
      12
    ],
    "514195ea": [
      12
    ],
    "17dfdff0": [
      12
    ],
    "3fee42e7": [
      12
    ],
    "16f3d9cd": [
      12
    ],
    "78dd9244": [
      12
    ],
    "118d608b": [
      12
    ],
    "17427e00": [
      12
    ],
    "9805e5d4": [
      12
    ],
    "6026d1f8": [
      12
    ],
    "9194a982": [
      12
    ],
    "c8f4585c": [
      10
    ],
    "6b78d5a7": [
      10
    ],
    "5c39eac5": [
      12
    ],
    "491c4c41": [
      12
    ],
    "c28f7d54": [
      12
    ],
    "43d8ca28": [
      12
    ],
    "35559f37": [
      12
    ],
    "17e6cd44": [
      12
    ],
    "1a0aecfb": [
      12
    ],
    "55e0dcae": [
      12
    ],
    "448dbe83": [
      12
    ],
    "2fb101a2": [
      12
    ],
    "b418e89a": [
      12
    ],
    "12abc5e8": [
      12
    ],
    "b17d6d92": [
      12
    ],
    "25b0a229": [
      12
    ],
    "08824b5a": [
      12
    ],
    "48e97c3c": [
      12
    ],
    "3c603223": [
      12
    ],
    "1ac35722": [
      12
    ],
    "087dbfa4": [
      12
    ],
    "8618dcc0": [
      12
    ],
    "0c7c7e0d": [
      12
    ],
    "02a63d0a": [
      12
    ],
    "97d71af0": [
      10
    ],
    "7dfdb1d2": [
      12
    ],
    "68362ae5": [
      10
    ],
    "4d451c32": [
      12
    ],
    "088b62c6": [
      12
    ],
    "1ca411c0": [
      12
    ],
    "ea96dfe0": [
      12
    ],
    "57fdc9ee": [
      12
    ],
    "70c64d74": [
      12
    ],
    "989feadc": [
      12
    ],
    "9843a6fa": [
      12
    ],
    "04934a78": [
      12
    ],
    "32b65394": [
      12
    ],
    "09d1fafb": [
      12
    ],
    "50bbd0b3": [
      12
    ],
    "3ccbc004": [
      12
    ],
    "26e9235a": [
      12
    ],
    "017eceb9": [
      10
    ],
    "1b0994f9": [
      10
    ],
    "d471fc06": [
      12
    ],
    "d7eaaec4": [
      12
    ],
    "30d00134": [
      12
    ],
    "42c12090": [
      12
    ],
    "4cc478c2": [
      12
    ],
    "0a03e248": [
      12
    ],
    "4de69648": [
      12
    ],
    "7a6e60b4": [
      12
    ],
    "51faf898": [
      12
    ],
    "88aec77e": [
      12
    ],
    "7bb611ce": [
      12
    ],
    "6a50878f": [
      12
    ],
    "59b8c090": [
      12
    ],
    "e5be4512": [
      12
    ],
    "5f0774bc": [
      12
    ],
    "22b9c1c4": [
      12
    ],
    "3199bc3f": [
      12
    ],
    "33bf80c2": [
      12
    ],
    "b36b32a0": [
      12
    ],
    "3e7c580d": [
      12
    ],
    "4ffe4dd4": [
      12
    ],
    "4bf4082d": [
      12
    ],
    "f6fde482": [
      12
    ],
    "4a6fad06": [
      12
    ],
    "823a4dde": [
      12
    ],
    "2611966c": [
      10
    ],
    "3822640d": [
      10
    ],
    "59039ab8": [
      10
    ],
    "6da68ec0": [
      12
    ],
    "1f476931": [
      12
    ],
    "98a679ba": [
      12
    ],
    "f713475a": [
      12
    ],
    "774fe1fb": [
      12
    ],
    "12ca7c54": [
      12
    ],
    "a1c18030": [
      12
    ],
    "44d0dd0d": [
      12
    ],
    "428fc8d1": [
      10
    ],
    "cfb35218": [
      10
    ],
    "cbe5bfd0": [
      10
    ],
    "48586ae0": [
      10
    ],
    "d4a07c20": [
      10
    ],
    "617d0fc5": [
      12
    ],
    "082faf9c": [
      10
    ],
    "b9a36a4c": [
      10
    ],
    "1ac69b3a": [
      10
    ],
    "c99cb82c": [
      12
    ],
    "1a39b56a": [
      10
    ],
    "138c07e0": [
      10
    ],
    "114a8c8e": [
      12
    ],
    "6f5e5f7c": [
      12
    ],
    "2767c372": [
      12
    ],
    "07fc4839": [
      12
    ],
    "caebde9e": [
      12
    ],
    "7e032824": [
      12
    ],
    "973e2602": [
      12
    ],
    "1f09e1a0": [
      12
    ],
    "05d97ad4": [
      12
    ],
    "73c9b762": [
      12
    ],
    "1a984236": [
      12
    ],
    "2e4554f4": [
      12
    ],
    "4c7b40da": [
      12
    ],
    "0fcb405e": [
      12
    ],
    "6efc419c": [
      12
    ],
    "3953392c": [
      12
    ],
    "5b816622": [
      12
    ],
    "d2efd2c4": [
      12
    ],
    "794e0e86": [
      12
    ],
    "5bbc9b04": [
      12
    ],
    "1f35c7b6": [
      12
    ],
    "146317ce": [
      12
    ],
    "72ab8dac": [
      12
    ],
    "676c7e7b": [
      12
    ],
    "4cb4dd71": [
      10
    ],
    "9d02ac9c": [
      10
    ],
    "24f81aa8": [
      12
    ],
    "030b0c18": [
      12
    ],
    "9e7cc960": [
      12
    ],
    "2df2b34d": [
      12
    ],
    "6cd388ac": [
      12
    ],
    "eff66246": [
      12
    ],
    "787c78c2": [
      12
    ],
    "f2be63dc": [
      12
    ],
    "5a4c95a0": [
      12
    ],
    "3a1eb750": [
      12
    ],
    "59339f24": [
      12
    ],
    "449f4ec4": [
      10
    ],
    "3cb10464": [
      10
    ],
    "0b049d10": [
      10
    ],
    "f2859ccc": [
      10
    ],
    "02e37921": [
      10
    ],
    "097dba93": [
      12
    ],
    "433a57ec": [
      12
    ],
    "22833ee4": [
      12
    ],
    "fd23ad26": [
      12
    ],
    "2e5b57e8": [
      12
    ],
    "684f10bb": [
      12
    ],
    "9c4b7fbe": [
      12
    ],
    "8cbb215c": [
      12
    ],
    "b8b975de": [
      12
    ],
    "e1d1f440": [
      12
    ],
    "946f88dc": [
      12
    ],
    "084057dd": [
      12
    ],
    "e7b14d4a": [
      12
    ],
    "d874e322": [
      12
    ],
    "43315fb0": [
      12
    ],
    "1a43830a": [
      12
    ],
    "86c163dc": [
      12
    ],
    "000ee1d9": [
      6
    ],
    "39c79ee0": [
      6
    ],
    "6b242a06": [
      6
    ],
    "f4b1cf2e": [
      13
    ],
    "574d9f22": [
      13
    ],
    "fd0805f8": [
      6
    ],
    "62617e04": [
      6
    ],
    "6625d234": [
      6
    ],
    "4172584f": [
      6
    ],
    "ea2565e2": [
      6
    ],
    "1ed0b9a0": [
      6
    ],
    "86f033c2": [
      6
    ],
    "7f05ade6": [
      13
    ],
    "7662ed52": [
      13
    ],
    "3dc7b792": [
      13
    ],
    "14e41e4f": [
      2
    ],
    "0fe86e0d": [
      6
    ],
    "12ed6184": [
      6
    ],
    "38a903e6": [
      6
    ],
    "d5a0b3b0": [
      6
    ],
    "5a00a350": [
      6
    ],
    "b174d6b2": [
      6
    ],
    "0ee6f77d": [
      6
    ],
    "4c5599f0": [
      6
    ],
    "1e4eabac": [
      6
    ],
    "7d80540a": [
      6
    ],
    "5702be74": [
      6
    ],
    "301f8f2c": [
      6
    ],
    "4c5eda3c": [
      6
    ],
    "25346c55": [
      6
    ],
    "5efca792": [
      6
    ],
    "3ebcfc20": [
      6
    ],
    "57cd7cc0": [
      6
    ],
    "0f05c7b0": [
      6
    ],
    "3fe273cb": [
      6
    ],
    "4bcc14c0": [
      6
    ],
    "317ed84d": [
      6
    ],
    "23f9a298": [
      6
    ],
    "34001beb": [
      6
    ],
    "1f3f6582": [
      6
    ],
    "e821e758": [
      6
    ],
    "29a419fc": [
      6
    ],
    "d82ea51c": [
      6
    ],
    "31704e97": [
      6
    ],
    "5ea44003": [
      6
    ],
    "9b333cbc": [
      6
    ],
    "3266510b": [
      6
    ],
    "53b56c8b": [
      6
    ],
    "475071ef": [
      6
    ],
    "d544fec2": [
      6
    ],
    "50fd5f8e": [
      6
    ],
    "d51ce986": [
      6
    ],
    "ac6a0264": [
      6
    ],
    "cc423f82": [
      6
    ],
    "24b74c0c": [
      6
    ],
    "9c3a69f8": [
      6
    ],
    "08db84e1": [
      6
    ],
    "cf8983d0": [
      6
    ],
    "391c8786": [
      6
    ],
    "7770a358": [
      6
    ],
    "57ef73dd": [
      6
    ],
    "1dbc1318": [
      6
    ],
    "49f633b4": [
      6
    ],
    "16d6b9d6": [
      6
    ],
    "00036afc": [
      6
    ],
    "4ce688a0": [
      6
    ],
    "6c0de25d": [
      6
    ],
    "0bd8b530": [
      6
    ],
    "f9ac3fd0": [
      6
    ],
    "51cf7a66": [
      8
    ],
    "cce4f230": [
      8
    ],
    "24780cc3": [
      8
    ],
    "14d68d5c": [
      8
    ],
    "2be5bf83": [
      8
    ],
    "5e660e16": [
      8
    ],
    "1726bbf6": [
      8
    ],
    "2b601b86": [
      8
    ],
    "5b2c7e13": [
      8
    ],
    "fbdb2b9a": [
      8
    ],
    "13a199f8": [
      8
    ],
    "623b1e27": [
      8
    ],
    "0dc9fe5a": [
      8
    ],
    "7751911d": [
      8
    ],
    "1f9e55c4": [
      8
    ],
    "54bad999": [
      2
    ],
    "5aa9dcb0": [
      2
    ],
    "18dfd420": [
      2
    ],
    "a662bccc": [
      2
    ],
    "3c4b78b0": [
      2
    ],
    "d796acee": [
      2
    ],
    "0638fd18": [
      2
    ],
    "67225f8b": [
      13
    ],
    "1bbb2732": [
      13
    ],
    "20eab376": [
      13
    ],
    "2655c5f0": [
      13
    ],
    "75d7f8b6": [
      13
    ],
    "7df44d40": [
      13
    ],
    "6cf1c496": [
      4
    ],
    "32bdebd2": [
      4
    ],
    "0840cc6a": [
      4
    ],
    "4dd63b26": [
      4
    ],
    "6adee1ea": [
      4
    ],
    "3bf33359": [
      5
    ],
    "22cd2eef": [
      5
    ],
    "668589a0": [
      5
    ],
    "7ed46159": [
      5
    ],
    "57aa2420": [
      5
    ],
    "f29c7a62": [
      7
    ],
    "7601cc14": [
      7
    ],
    "607cb6b2": [
      7
    ],
    "ca3e322c": [
      7
    ],
    "46c55bf2": [
      7
    ],
    "fb7399ce": [
      3
    ],
    "9c6c10dc": [
      3
    ],
    "20f874a8": [
      3
    ],
    "b7846030": [
      3
    ],
    "20ad2c30": [
      3
    ]
  },
  "assetsMapping": {
    "bba68bf6": [
      "13c5661.js",
      "25c4d93.js",
      "38f26bc.js",
      "3be277b.js",
      "4828718.js",
      "5c3d831.js",
      "5d961e2.js",
      "ee95317.js"
    ],
    "6fca0322": [
      "73c76db.js"
    ],
    "1a3ae26b": [
      "86ad62f.js"
    ],
    "085a35c4": [
      "e1782c0.js"
    ]
  }
}